Metadata-Version: 2.1
Name: django-tailwind-comments
Version: 2.7.2
Summary: Django Comment app. It can be associated with any given model.
Home-page: https://github.com/lordmahyar/django-tailwind-comments
Author: Mahyar
Author-email: mmaahhyyaarr@gmail.com
License: MIT
Project-URL: Documentation, https://github.com/lordmahyar/django-tailwind-comments/README.md
Project-URL: Source Code, https://github.com/lordmahyar/django-tailwind-comments
Keywords: django comment comments ajax
Provides-Extra: markdown
License-File: LICENSE
